[
    {
        "id": "post-3",
        "author": "user-2",
        "image": "https://media.giphy.com/media/v1.Y2lkPTc5MGI3NjExb2V6cWJlZnYzcXY4ODU0NnV1bjN1ZGxlcHVlajRqenh6b2gxN3pqbSZlcD12MV9naWZzX3NlYXJjaCZjdD1n/GSgWBrpHeRdWE/giphy.gif",
        "text": "pin8 dancing",
        "date": "2025-05-10T10:55:50.950Z",
        "likes": []
    },
    {
        "id": "post-7",
        "author": "user-10",
        "image": "https://media.giphy.com/media/cdIvfaC6Yk8OL3zUly/giphy.gif?cid=82a1493btbdkcpahvh1wf187ckczz9n2fdh8380aw1okm2ic&ep=v1_gifs_trending&rid=giphy.gif&ct=g",
        "text": "happy saturday in swimming pool",
        "date": "2025-05-17T14:42:42.430Z",
        "likes": []
    },
    {
        "id": "post-8",
        "author": "user-11",
        "image": "https://media.giphy.com/media/v1.Y2lkPTc5MGI3NjExMTBlMXJqZXZsbnJsbW56amZyOTdsYXR0cXpkbHpvODRwcTQwNnEwdyZlcD12MV9naWZzX3RyZW5kaW5nJmN0PWc/Af7J60LV3SjIqWXzzj/giphy.gif",
        "text": "my lovely cat",
        "date": "2025-05-17T14:46:57.532Z",
        "likes": []
    },
    {
        "id": "post-9",
        "author": "user-10",
        "image": "https://media.giphy.com/media/1qB3EwE3c54A/giphy.gif?cid=82a1493bl4xmrnawbok4waejtkc68jwoch75acsx5sdk5b7z&ep=v1_gifs_trending&rid=giphy.gif&ct=g",
        "text": "refreshing ideas",
        "date": "2025-05-17T14:48:26.389Z",
        "likes": []
    }
]